[
  {
    "title": "Questa maglia √® pazzesca‚öĹūüĒ•",
    "link": "https://www.youtube.com/shorts/m3c64m6GQqU",
    "published": "2026-07-05",
    "videoId": "m3c64m6GQqU"
  },
  {
    "title": "ūüĒ•EKHATOR alla JUVENTUS: possibile sorpresa al #Fantacalcio?",
    "link": "https://www.youtube.com/shorts/uLQoIz0Vxzk",
    "published": "2026-07-02",
    "videoId": "uLQoIz0Vxzk"
  },
  {
    "title": "Analisi 5 NUOVI ARRIVI: prime INDICAZIONI al Fantacalcio",
    "link": "https://www.youtube.com/watch?v=ew019NX82Tk",
    "published": "2026-07-02",
    "videoId": "ew019NX82Tk"
  },
  {
    "title": "Gli ALLENATORI al Fantacalcio: la mia CLASSIFICA di appetibilit√†",
    "link": "https://www.youtube.com/watch?v=ELlFGnjlLxk",
    "published": "2026-06-30",
    "videoId": "ELlFGnjlLxk"
  },
  {
    "title": "Ti svelo LO SPOGLIATOIOūüĎČLa mia APP ESCLUSIVA del Fantacalcio",
    "link": "https://www.youtube.com/shorts/NVsP2XAp4fM",
    "published": "2026-06-29",
    "videoId": "NVsP2XAp4fM"
  },
  {
    "title": "Ho creato un'APP per chi vuole vincere al Fantacalcio",
    "link": "https://www.youtube.com/watch?v=ApSo40lnjHw",
    "published": "2026-06-29",
    "videoId": "ApSo40lnjHw"
  },
  {
    "title": "11 NOMI da RICONFERMARE al FANTACALCIO 2026/27 a pochi CREDITIūüüĘ",
    "link": "https://www.youtube.com/watch?v=LKEmdpW-yy0",
    "published": "2026-05-29",
    "videoId": "LKEmdpW-yy0"
  },
  {
    "title": "Le PAGELLE del FANTACALCIO 2025/26 Promossi Rimandati e BocciatiūüĎČEcco i VOTI FINALI del Mister",
    "link": "https://www.youtube.com/watch?v=SoJbTBTJJUc",
    "published": "2026-05-26",
    "videoId": "SoJbTBTJJUc"
  },
  {
    "title": "ūüéôÔłŹLIVE CONSIGLI FANTACALCIO 38 Giornata CHI SCHIERAREūüĎČULTIME DAI CAMPI",
    "link": "https://www.youtube.com/watch?v=NSjI9NeOSGs",
    "published": "2026-05-23",
    "videoId": "NSjI9NeOSGs"
  },
  {
    "title": "5 ATTACCANTI NON SCONTATI per la 38¬™ Giornata al¬†#Fantacalcio",
    "link": "https://www.youtube.com/shorts/4Pf7NsKkPLY",
    "published": "2026-05-21",
    "videoId": "4Pf7NsKkPLY"
  },
  {
    "title": "5 CONSIGLIATI e SCONSIGLIATI x Repartoūüö¶38 Giornata FANTACALCIOūüĎČL'11 del MISTER",
    "link": "https://www.youtube.com/watch?v=6vLiUsxY1dI",
    "published": "2026-05-21",
    "videoId": "6vLiUsxY1dI"
  },
  {
    "title": "CHI SCHIERARE Fantacalcio 38 GIORNATAūüĎČI miei INDICI SCHIERABILIT√ÄūüĒ•Analisi e Pronostici Partite",
    "link": "https://www.youtube.com/watch?v=AvcRWUOd1K8",
    "published": "2026-05-20",
    "videoId": "AvcRWUOd1K8"
  },
  {
    "title": "ūüéôÔłŹFANTACALCIO LiveūüŹÜLEGHE ABBONATI: Vincitori, Commenti e Discussioni‚≠źÔłŹFANTAMISTER CLUB",
    "link": "https://www.youtube.com/watch?v=7U_ExGNZNGc",
    "published": "2026-05-20",
    "videoId": "7U_ExGNZNGc"
  },
  {
    "title": "ūüŹÜ Ho VINTO anche il #Fantacalcio MANTRA, DOBLETE!",
    "link": "https://www.youtube.com/shorts/Xpq0Chjsx8s",
    "published": "2026-05-18",
    "videoId": "Xpq0Chjsx8s"
  },
  {
    "title": "ūüéôÔłŹLIVE CONSIGLI FANTACALCIO 37 Giornata CHI SCHIERAREūüĎČULTIME DAI CAMPI",
    "link": "https://www.youtube.com/watch?v=C69GjwqbqZs",
    "published": "2026-05-17",
    "videoId": "C69GjwqbqZs"
  }
]